borco_nanobind_example/__init__.py
borco_nanobind_example/_borco_nanobind_example_impl.pyd
borco_nanobind_example/_borco_nanobind_example_impl.pyi
borco_nanobind_example/py.typed
borco_nanobind_example-0.0.3.dist-info/METADATA
borco_nanobind_example-0.0.3.dist-info/WHEEL
borco_nanobind_example-0.0.3.dist-info/licenses/LICENSE
borco_nanobind_example-0.0.3.dist-info/RECORD
